{
    "type": "taskUniversal",
    "actions": {
        "abortActions": [],
        "emailNotifications": [],
        "setVariableActions": [],
        "snmpNotifications": [],
        "systemOperations": []
    },
    "agent": null,
    "agentCluster": null,
    "agentClusterVar": null,
    "agentVar": "${${ops_system_identifier}_windows_agent}",
    "autoCleanup": false,
    "broadcastCluster": null,
    "broadcastClusterVar": null,
    "choiceField1": {
        "label": "Logging Level",
        "name": "loglevel",
        "value": "NotSet"
    },
    "choiceField2": {
        "label": "Command or Script",
        "name": "type",
        "value": "Command"
    },
    "choiceField3": {
        "label": "Script OS Type",
        "name": "os",
        "value": "Unix"
    },
    "cpDuration": null,
    "cpDurationUnit": "Minutes",
    "createConsole": false,
    "credentialField1": {
        "label": "Remote SSH Credential",
        "name": "credential",
        "value": "colin.cocksedge"
    },
    "credentials": null,
    "credentialsVar": null,
    "customField1": {
        "label": "Owner",
        "value": null
    },
    "customField2": {
        "label": null,
        "value": null
    },
    "desktopInteract": false,
    "efDayConstraint": "None",
    "efDuration": "00:00:00:00",
    "efEnabled": false,
    "efNthAmount": 5,
    "efOffsetDuration": null,
    "efOffsetDurationUnit": "Minutes",
    "efOffsetPercentage": 0,
    "efOffsetType": "Percentage",
    "efTime": "00:00",
    "efType": "Time",
    "elevateUser": false,
    "environment": [],
    "exclusiveTasks": [],
    "exclusiveWithSelf": false,
    "executionRestriction": "None",
    "exitCodeOutput": null,
    "exitCodeProcessing": "Success Exitcode Range",
    "exitCodeText": null,
    "exitCodes": "0",
    "exportReleaseLevel": "7.3.0.0",
    "exportTable": "ops_task_universal",
    "firstRun": "",
    "holdResources": false,
    "intField1": {
        "label": "Remote SSH Port",
        "name": "port",
        "value": 2222
    },
    "largeTextField1": {
        "label": "Command",
        "name": "command",
        "value": "pwd"
    },
    "lastRun": "",
    "lfDayConstraint": "None",
    "lfDuration": "00:00:00:00",
    "lfEnabled": false,
    "lfNthAmount": 5,
    "lfOffsetDuration": null,
    "lfOffsetDurationUnit": "Minutes",
    "lfOffsetPercentage": 0,
    "lfOffsetType": "Percentage",
    "lfTime": "00:00",
    "lfType": "Time",
    "logLevel": "Inherited",
    "lsDayConstraint": "None",
    "lsDuration": "00:00:00:00",
    "lsEnabled": false,
    "lsNthAmount": 5,
    "lsTime": "00:00",
    "lsType": "Time",
    "name": "Jscape SSH Server",
    "notes": [],
    "opswiseGroups": [],
    "outputConditionOperator": "=",
    "outputConditionStrategy": "Match Any",
    "outputConditionValue": null,
    "outputContentType": null,
    "outputFailureOnly": false,
    "outputPathExpression": null,
    "outputReturnFile": null,
    "outputReturnNline": "100",
    "outputReturnSline": "1",
    "outputReturnText": null,
    "outputReturnType": "NONE",
    "outputType": "STDOUT",
    "resPriority": 10,
    "resolveNameImmediately": false,
    "restrictionPeriod": "None",
    "restrictionPeriodAfterDate": null,
    "restrictionPeriodAfterTime": null,
    "restrictionPeriodBeforeDate": null,
    "restrictionPeriodBeforeTime": null,
    "restrictionPeriodDateList": [],
    "retainSysIds": true,
    "retryExitCodes": null,
    "retryIndefinitely": false,
    "retryInterval": 60,
    "retryMaximum": 0,
    "retrySuppressFailure": false,
    "runCount": 0,
    "runTime": 0,
    "runtimeDir": null,
    "scriptField1": {
        "label": "Script",
        "name": "script",
        "value": null
    },
    "startHeld": false,
    "startHeldReason": null,
    "summary": null,
    "sysId": "53e9466d0dad4b639ca72b97e608c81f",
    "template": "SSH",
    "textField1": {
        "label": "Remote SSH Server",
        "name": "host",
        "value": "sbus77"
    },
    "timeZonePref": "-- System Default --",
    "twDelayAmount": null,
    "twDelayDuration": "00:00:00:00",
    "twDelayType": "None",
    "twWaitAmount": null,
    "twWaitDayConstraint": "None",
    "twWaitDuration": "00:00:00:00",
    "twWaitTime": "00:00",
    "twWaitType": "None",
    "twWorkflowOnly": "-- System Default --",
    "userEstimatedDuration": null,
    "variables": [],
    "version": 2,
    "virtualResources": [],
    "waitForOutput": false
}